README.md
setup.cfg
setup.py
take_a_break/__init__.py
take_a_break/__main__.py
take_a_break/configuration.py
take_a_break/tbmain.py
take_a_break/tbmenu.py
take_a_break/tbsettings.py
take_a_break.egg-info/PKG-INFO
take_a_break.egg-info/SOURCES.txt
take_a_break.egg-info/dependency_links.txt
take_a_break.egg-info/requires.txt
take_a_break.egg-info/top_level.txt
take_a_break/providers/__init__.py
take_a_break/providers/unsplash_api.py
take_a_break/resources/icon.ico
take_a_break/resources/random.png