Metadata-Version: 2.1
Name: take-a-break
Version: 0.3
Summary: Reminds you to take breaks
Home-page: https://github.com/paulbrodner/take-a-break
Author: Paul Brodner
Author-email: paulbrodner@gmail.com
License: UNKNOWN
Project-URL: Source, https://github.com/paulbrodner/take-a-break
Project-URL: Tracker, https://github.com/paulbrodner/take-a-break/issues
Platform: UNKNOWN
Classifier: Development Status :: 1 - Planning
Classifier: Programming Language :: Python :: 3
Classifier: License :: OSI Approved :: GNU General Public License v3 (GPLv3)
Classifier: Topic :: Utilities
Classifier: Operating System :: OS Independent
Requires-Python: >=3.8
